kcollections/_Kcounter.so
kcollections/_Kdict.so
kcollections/_Kset.so
kcollections/__init__.py
kcollections-1.0.5.dist-info/LICENSE
kcollections-1.0.5.dist-info/METADATA
kcollections-1.0.5.dist-info/WHEEL
kcollections-1.0.5.dist-info/top_level.txt
kcollections-1.0.5.dist-info/RECORD
