Metadata-Version: 2.1
Name: kcollections
Version: 1.0.5
Summary: A BloomFilterTrie implementation to be generally applicable for genomic applications.
Home-page: https://github.com/masakistan/kcollections
Author: M. Stanley Fujimoto and Cole A. Lyman
Author-email: sfujimoto@gmail.com
License: GPLv3
Platform: UNKNOWN
